gigantumcli/__init__.py
gigantumcli/actions.py
gigantumcli/changelog.py
gigantumcli/cli.py
gigantumcli/config.py
gigantumcli/dockerinterface.py
gigantumcli/server.py
gigantumcli/utilities.py
gigantumcli/commands/__init__.py
gigantumcli/commands/config.py
gigantumcli/commands/feedback.py
gigantumcli/commands/install.py
gigantumcli/commands/server.py
gigantumcli/commands/start.py
gigantumcli/commands/stop.py
gigantumcli/commands/update.py
gigantumcli/tests/__init__.py
gigantumcli/tests/fixtures.py
gigantumcli/tests/test_actions.py
gigantumcli/tests/test_changelog.py
gigantumcli/tests/test_cleanup_containers.py
gigantumcli/tests/test_config.py
gigantumcli/tests/test_install.py
gigantumcli/tests/test_server.py
gigantumcli/tests/test_start.py
gigantumcli/tests/test_stop.py
gigantumcli/tests/test_update.py
gigantum-1.3.4.dist-info/LICENSE
gigantum-1.3.4.dist-info/METADATA
gigantum-1.3.4.dist-info/WHEEL
gigantum-1.3.4.dist-info/entry_points.txt
gigantum-1.3.4.dist-info/top_level.txt
gigantum-1.3.4.dist-info/RECORD
