Metadata-Version: 2.1
Name: gigantum
Version: 1.3.4
Summary: CLI for the Gigantum Client
Home-page: https://github.com/gigantum/gigantum-cli
Author: Gigantum, Inc.
Author-email: support@gigantum.com
License: MIT
Keywords: data-science,science,gigantum,open-science,machine-learning
Platform: UNKNOWN
Classifier: Development Status :: 4 - Beta
Classifier: Programming Language :: Python :: 3.8
Classifier: Programming Language :: Python :: 3.7
Classifier: Programming Language :: Python :: 3.6
Classifier: Programming Language :: Python :: 3.5
Classifier: Programming Language :: Python :: 3.4
Requires-Dist: docker (==4.3.1)
Requires-Dist: six (==1.12.0)
Requires-Dist: PyYAML (==5.4.1)
Requires-Dist: click (==7.1.2)
